disentanglement_error/__init__.py
disentanglement_error/decreasing_dataset.py
disentanglement_error/disentangling_model.py
disentanglement_error/error_metric.py
disentanglement_error/label_noise.py
disentanglement_error/util.py
disentanglement_error-0.1.4.dist-info/METADATA
disentanglement_error-0.1.4.dist-info/WHEEL
disentanglement_error-0.1.4.dist-info/top_level.txt
disentanglement_error-0.1.4.dist-info/RECORD
