Metadata-Version: 2.4
Name: disentanglement-error
Version: 0.1.4
Summary: Measure whether aleatoric and epistemic uncertainty are estimated orthogonally
Project-URL: source, https://github.com/ivopascal/disentanglement_error
Requires-Python: >=3.11
Requires-Dist: notebook>=7.4.5
Requires-Dist: numpy>=1.26.4
Requires-Dist: scikit-learn>=1.7.1
Requires-Dist: pandas>=2.3.1
